seisclient/__init__.py
seisclient/db.py
seisclient/seisclient.py
seisclient-0.0.2.dist-info/LICENSE
seisclient-0.0.2.dist-info/METADATA
seisclient-0.0.2.dist-info/WHEEL
seisclient-0.0.2.dist-info/top_level.txt
seisclient-0.0.2.dist-info/RECORD
